DESCRIPTION.rst
LICENSE
MANIFEST.in
README.rst
setup.cfg
setup.py
ardtools/__init__.py
ardtools/cli.py
ardtools/tools.py
ardtools/util.py
ardtools/version.py
ardtools.egg-info/PKG-INFO
ardtools.egg-info/SOURCES.txt
ardtools.egg-info/dependency_links.txt
ardtools.egg-info/entry_points.txt
ardtools.egg-info/not-zip-safe
ardtools.egg-info/top_level.txt