Metadata-Version: 1.1
Name: ardtools
Version: 0.1.0a2
Summary: Tools to control Mac OS X Screen Sharing from the Command         Line
Home-page: https://bitbucket.org/apollonia/screen-sharing-restart 
Author: Erehwon Tools
Author-email: devops@erehwon.xyz
License: New BSD
Download-URL: https://bitbucket.org/apollonia/screen-sharing-restart/get/master.tar.gz
Keywords: system vnc ARD apple remote desktop screen sharing mac osx
Platform: UNKNOWN
Classifier: Development Status :: 3 - Alpha
Classifier: Intended Audience :: System Administrators
Classifier: License :: OSI Approved :: BSD License
Classifier: Programming Language :: Python :: 2.7
Classifier: Topic :: System :: Systems Administration
